[
  {
    "n_months": 8,
    "avg_ret": 1570.8095378007247,
    "med_ret": 939.4273118913386,
    "std_ret": 1837.0922754767535,
    "avg_wr": 64.82816293428034,
    "profitable": 8,
    "total_months": 8,
    "worst_dip": -4.61138285985424,
    "results": [
      {
        "seed": 777,
        "month": "2024-08",
        "ret": 875.6687664791679,
        "wr": 59.06432748538012,
        "trades": 342,
        "liq": 0,
        "min_vs_init": -4.047391052119265
      },
      {
        "seed": 777,
        "month": "2024-12",
        "ret": 2891.3530966154417,
        "wr": 67.84313725490196,
        "trades": 255,
        "liq": 0,
        "min_vs_init": -3.6500620096794445
      },
      {
        "seed": 777,
        "month": "2025-03",
        "ret": 5545.89187675219,
        "wr": 66.27906976744185,
        "trades": 430,
        "liq": 0,
        "min_vs_init": -0.7919683199999916
      },
      {
        "seed": 777,
        "month": "2025-07",
        "ret": 89.60431678167868,
        "wr": 72.91666666666666,
        "trades": 48,
        "liq": 0,
        "min_vs_init": -4.61138285985424
      },
      {
        "seed": 123,
        "month": "2024-02",
        "ret": 1003.1858573035092,
        "wr": 65.51724137931035,
        "trades": 174,
        "liq": 0,
        "min_vs_init": -3.766986441872544
      },
      {
        "seed": 123,
        "month": "2024-03",
        "ret": 225.58949022191337,
        "wr": 60.544217687074834,
        "trades": 147,
        "liq": 0,
        "min_vs_init": 0.0
      },
      {
        "seed": 123,
        "month": "2024-09",
        "ret": 1488.4052187873997,
        "wr": 57.324840764331206,
        "trades": 314,
        "liq": 0,
        "min_vs_init": 0.0
      },
      {
        "seed": 123,
        "month": "2026-01",
        "ret": 446.7776794644965,
        "wr": 69.1358024691358,
        "trades": 243,
        "liq": 0,
        "min_vs_init": -0.5677082399999978
      }
    ],
    "name": "MC10_B0.5_DLL8_TR2",
    "params": {
      "MAX_CONCURRENT": 10,
      "BE_R": 0.5,
      "DAILY_LOSS_LIMIT": 8.0,
      "TRAIL_R": 2.0
    }
  },
  {
    "n_months": 8,
    "avg_ret": 1251.540721794271,
    "med_ret": 831.0871108719797,
    "std_ret": 1555.0799856775825,
    "avg_wr": 64.39180306714061,
    "profitable": 8,
    "total_months": 8,
    "worst_dip": -4.337424336986217,
    "results": [
      {
        "seed": 777,
        "month": "2024-08",
        "ret": 966.4410334610444,
        "wr": 60.093896713615024,
        "trades": 426,
        "liq": 0,
        "min_vs_init": -2.5007888533857825
      },
      {
        "seed": 777,
        "month": "2024-12",
        "ret": 1978.9995246820965,
        "wr": 70.7395498392283,
        "trades": 311,
        "liq": 0,
        "min_vs_init": -2.4638521551406334
      },
      {
        "seed": 777,
        "month": "2025-03",
        "ret": 4796.822089207441,
        "wr": 67.46765249537893,
        "trades": 541,
        "liq": 0,
        "min_vs_init": 0.0
      },
      {
        "seed": 777,
        "month": "2025-07",
        "ret": 45.082887533752604,
        "wr": 65.21739130434783,
        "trades": 69,
        "liq": 0,
        "min_vs_init": -4.337424336986217
      },
      {
        "seed": 123,
        "month": "2024-02",
        "ret": 695.733188282915,
        "wr": 64.38356164383562,
        "trades": 219,
        "liq": 0,
        "min_vs_init": -2.5420215229962184
      },
      {
        "seed": 123,
        "month": "2024-03",
        "ret": 194.42385413085103,
        "wr": 62.42038216560509,
        "trades": 157,
        "liq": 0,
        "min_vs_init": 0.0
      },
      {
        "seed": 123,
        "month": "2024-09",
        "ret": 970.7644947731426,
        "wr": 59.07990314769975,
        "trades": 413,
        "liq": 0,
        "min_vs_init": 0.0
      },
      {
        "seed": 123,
        "month": "2026-01",
        "ret": 364.0587022829234,
        "wr": 65.73208722741433,
        "trades": 321,
        "liq": 0,
        "min_vs_init": -0.3870737999999929
      }
    ],
    "name": "MC8_P15_DLL5_TR2",
    "params": {
      "MAX_CONCURRENT": 8,
      "POSITION_PCT": 15.0,
      "BE_R": 0.5,
      "DAILY_LOSS_LIMIT": 5.0,
      "TRAIL_R": 2.0
    }
  },
  {
    "n_months": 8,
    "avg_ret": 914.6990900266695,
    "med_ret": 587.2897806752608,
    "std_ret": 1145.7489090156864,
    "avg_wr": 61.94281456644056,
    "profitable": 8,
    "total_months": 8,
    "worst_dip": -2.483137857160711,
    "results": [
      {
        "seed": 777,
        "month": "2024-08",
        "ret": 690.8058354087337,
        "wr": 57.014388489208635,
        "trades": 556,
        "liq": 0,
        "min_vs_init": -0.7478679999999849
      },
      {
        "seed": 777,
        "month": "2024-12",
        "ret": 1265.7702906638503,
        "wr": 68.43373493975903,
        "trades": 415,
        "liq": 0,
        "min_vs_init": -1.5210703192894526
      },
      {
        "seed": 777,
        "month": "2025-03",
        "ret": 3591.2266455937106,
        "wr": 67.84313725490196,
        "trades": 765,
        "liq": 0,
        "min_vs_init": -0.6298883999999783
      },
      {
        "seed": 777,
        "month": "2025-07",
        "ret": 53.8671448017924,
        "wr": 59.34065934065934,
        "trades": 91,
        "liq": 0,
        "min_vs_init": -2.483137857160711
      },
      {
        "seed": 123,
        "month": "2024-02",
        "ret": 483.7737259417879,
        "wr": 62.454873646209386,
        "trades": 277,
        "liq": 0,
        "min_vs_init": -1.681714030801429
      },
      {
        "seed": 123,
        "month": "2024-03",
        "ret": 121.45149388170964,
        "wr": 60.12658227848101,
        "trades": 158,
        "liq": 0,
        "min_vs_init": 0.0
      },
      {
        "seed": 123,
        "month": "2024-09",
        "ret": 692.7709061265114,
        "wr": 54.97287522603978,
        "trades": 553,
        "liq": 0,
        "min_vs_init": -0.6121079999999779
      },
      {
        "seed": 123,
        "month": "2026-01",
        "ret": 417.92667779525976,
        "wr": 65.35626535626535,
        "trades": 407,
        "liq": 0,
        "min_vs_init": -0.2580492000000101
      }
    ],
    "name": "MC10_P10_B0.5_DLL5",
    "params": {
      "MAX_CONCURRENT": 10,
      "POSITION_PCT": 10.0,
      "BE_R": 0.5,
      "DAILY_LOSS_LIMIT": 5.0
    }
  },
  {
    "n_months": 8,
    "avg_ret": 1374.3467059363259,
    "med_ret": 814.9650643019756,
    "std_ret": 1825.117144822755,
    "avg_wr": 64.7319316652114,
    "profitable": 8,
    "total_months": 8,
    "worst_dip": -2.5420215229962184,
    "results": [
      {
        "seed": 777,
        "month": "2024-08",
        "ret": 965.2524781478714,
        "wr": 60.63569682151589,
        "trades": 409,
        "liq": 0,
        "min_vs_init": 0.0
      },
      {
        "seed": 777,
        "month": "2024-12",
        "ret": 1996.5192455856443,
        "wr": 71.34146341463415,
        "trades": 328,
        "liq": 0,
        "min_vs_init": -2.3016202262406193
      },
      {
        "seed": 777,
        "month": "2025-03",
        "ret": 5630.530476723798,
        "wr": 70.46728971962617,
        "trades": 535,
        "liq": 0,
        "min_vs_init": 0.0
      },
      {
        "seed": 777,
        "month": "2025-07",
        "ret": 63.44756241520339,
        "wr": 64.7887323943662,
        "trades": 71,
        "liq": 0,
        "min_vs_init": -2.1241901170238386
      },
      {
        "seed": 123,
        "month": "2024-02",
        "ret": 664.6776504560798,
        "wr": 66.3594470046083,
        "trades": 217,
        "liq": 0,
        "min_vs_init": -2.5420215229962184
      },
      {
        "seed": 123,
        "month": "2024-03",
        "ret": 219.96926500828783,
        "wr": 61.935483870967744,
        "trades": 155,
        "liq": 0,
        "min_vs_init": 0.0
      },
      {
        "seed": 123,
        "month": "2024-09",
        "ret": 1084.6164936941434,
        "wr": 56.683168316831676,
        "trades": 404,
        "liq": 0,
        "min_vs_init": 0.0
      },
      {
        "seed": 123,
        "month": "2026-01",
        "ret": 369.7604754595795,
        "wr": 65.6441717791411,
        "trades": 326,
        "liq": 0,
        "min_vs_init": -0.3870737999999929
      }
    ],
    "name": "MC8_P15_DLL5_RR6",
    "params": {
      "MAX_CONCURRENT": 8,
      "POSITION_PCT": 15.0,
      "BE_R": 0.5,
      "DAILY_LOSS_LIMIT": 5.0,
      "RR": 6.0
    }
  },
  {
    "n_months": 8,
    "avg_ret": 989.9451661553666,
    "med_ret": 587.2897806752608,
    "std_ret": 1348.4713836339372,
    "avg_wr": 61.87280647785662,
    "profitable": 8,
    "total_months": 8,
    "worst_dip": -2.483137857160711,
    "results": [
      {
        "seed": 777,
        "month": "2024-08",
        "ret": 690.8058354087337,
        "wr": 57.014388489208635,
        "trades": 556,
        "liq": 0,
        "min_vs_init": -0.7478679999999849
      },
      {
        "seed": 777,
        "month": "2024-12",
        "ret": 1265.7702906638503,
        "wr": 68.43373493975903,
        "trades": 415,
        "liq": 0,
        "min_vs_init": -1.5210703192894526
      },
      {
        "seed": 777,
        "month": "2025-03",
        "ret": 4193.195254623287,
        "wr": 67.28307254623044,
        "trades": 703,
        "liq": 0,
        "min_vs_init": -0.6298883999999783
      },
      {
        "seed": 777,
        "month": "2025-07",
        "ret": 53.8671448017924,
        "wr": 59.34065934065934,
        "trades": 91,
        "liq": 0,
        "min_vs_init": -2.483137857160711
      },
      {
        "seed": 123,
        "month": "2024-02",
        "ret": 483.7737259417879,
        "wr": 62.454873646209386,
        "trades": 277,
        "liq": 0,
        "min_vs_init": -1.681714030801429
      },
      {
        "seed": 123,
        "month": "2024-03",
        "ret": 121.45149388170964,
        "wr": 60.12658227848101,
        "trades": 158,
        "liq": 0,
        "min_vs_init": 0.0
      },
      {
        "seed": 123,
        "month": "2024-09",
        "ret": 692.7709061265114,
        "wr": 54.97287522603978,
        "trades": 553,
        "liq": 0,
        "min_vs_init": -0.6121079999999779
      },
      {
        "seed": 123,
        "month": "2026-01",
        "ret": 417.92667779525976,
        "wr": 65.35626535626535,
        "trades": 407,
        "liq": 0,
        "min_vs_init": -0.2580492000000101
      }
    ],
    "name": "MC10_P10_B0.5_DLL8",
    "params": {
      "MAX_CONCURRENT": 10,
      "POSITION_PCT": 10.0,
      "BE_R": 0.5,
      "DAILY_LOSS_LIMIT": 8.0
    }
  }
]